{
  "abilities": [
    {
      "cmds": [
        {
          "cost": null,
          "id": "Stop",
          "index": 0,
          "meta": {
            "icon": "btn-command-stop",
            "kind": "command"
          },
          "requires": null
        }
      ],
      "id": "stop",
      "index": 41
    },
    {
      "cmds": [
        {
          "cost": null,
          "id": "Execute",
          "index": 0,
          "meta": {
            "icon": "btn-command-attack",
            "kind": "command"
          },
          "requires": null
        }
      ],
      "id": "attack",
      "index": 46
    },
    {
      "cmds": [
        {
          "cost": null,
          "id": "Move",
          "index": 0,
          "meta": {
            "icon": "btn-command-move",
            "kind": "command"
          },
          "requires": null
        },
        {
          "cost": null,
          "id": "Patrol",
          "index": 1,
          "meta": {
            "icon": "btn-command-patrol",
            "kind": "command"
          },
          "requires": null
        },
        {
          "cost": null,
          "id": "HoldPos",
          "index": 2,
          "meta": {
            "icon": "btn-command-holdposition",
            "kind": "command"
          },
          "requires": null
        }
      ],
      "id": "move",
      "index": 43
    },
    {
      "cmds": [
        {
          "cost": null,
          "id": "Execute",
          "index": 0,
          "meta": {
            "icon": "btn-ability-terran-liberator-agmode",
            "kind": "command"
          },
          "requires": null
        }
      ],
      "id": "LiberatorAGTarget",
      "index": 617
    }
  ],
  "armor": {
    "max": 3,
    "start": 0
  },
  "attributes": [
    "Armored",
    "Mechanical"
  ],
  "cost": {
    "cooldown": 0,
    "minerals": 150,
    "supply": 3,
    "time": 60,
    "vespene": 125
  },
  "id": "Liberator",
  "life": {
    "max": 180,
    "regen": 0.0,
    "start": 180
  },
  "meta": {
    "icon": "btn-unit-terran-liberator",
    "race": "Terr"
  },
  "misc": {
    "cargo_size": 0,
    "footprint": null,
    "radius": 0.75,
    "sight_radius": 10,
    "supply": -3.0
  },
  "movement": {
    "acceleration": 3.5,
    "deceleration": 0.0,
    "kind": "Fly",
    "speed": 3.375,
    "turn_rate": 1499.94140625
  },
  "producer": {
    "id": "Starport"
  },
  "requires": [],
  "score": {
    "build": 275,
    "kill": 275
  },
  "shield_armor": {
    "max": 0,
    "start": 0
  },
  "shields": null,
  "state": {
    "ability": {
      "cmds": [],
      "current_cmd": {
        "cost": null,
        "id": null,
        "index": null,
        "meta": {
          "icon": "",
          "kind": ""
        },
        "requires": null
      },
      "id": null,
      "index": null
    }
  },
  "strengths": [
    {
      "id": "SiegeTank"
    },
    {
      "id": "Ultralisk"
    },
    {
      "id": "Phoenix"
    }
  ],
  "upgrades": [],
  "weaknesses": [
    {
      "id": "Battlecruiser"
    },
    {
      "id": "Corruptor"
    },
    {
      "id": "Tempest"
    }
  ]
}